browse_mcp/__init__.py
browse_mcp/baidu_search_example.py
browse_mcp/baidu_search_playwright_server.py
browse_mcp/browse_manager.py
browse_mcp/browse_operation_server.py
browse_mcp/css/__init__.py
browse_mcp/css/page_elements_mark.css
browse_mcp/script/__init__.py
browse_mcp/script/page_elements_choose.js
browse_mcp/script/page_elements_mark.js
browse_mcp/tools/__init__.py
browse_mcp/tools/file_tools.py
browse_mcp/tools/playwright_tools.py
moggy_mcp_server-0.1.53.dist-info/METADATA
moggy_mcp_server-0.1.53.dist-info/WHEEL
moggy_mcp_server-0.1.53.dist-info/entry_points.txt
moggy_mcp_server-0.1.53.dist-info/licenses/LICENSE
moggy_mcp_server-0.1.53.dist-info/RECORD
